rlwsd/__init__.py
rlwsd/download.py
rlwsd/stopwords.txt
rlwsd/utils.py
rlwsd/w2v_client.py
rlwsd/w2v_server.py
rlwsd/wsd.py
rlwsd-0.1.2.dist-info/DESCRIPTION.rst
rlwsd-0.1.2.dist-info/METADATA
rlwsd-0.1.2.dist-info/RECORD
rlwsd-0.1.2.dist-info/WHEEL
rlwsd-0.1.2.dist-info/entry_points.txt
rlwsd-0.1.2.dist-info/metadata.json
rlwsd-0.1.2.dist-info/top_level.txt
