Metadata-Version: 2.0
Name: rlwsd
Version: 0.1.2
Summary: Word sense disambiguation library
Home-page: https://github.com/lopuhin/sensefreq
Author: Konstantin Lopukhin, Grigory Nosyrev
Author-email: kostia.lopuhin@gmail.com
License: MIT license
Platform: UNKNOWN
Classifier: Development Status :: 3 - Alpha
Classifier: License :: OSI Approved :: MIT License
Classifier: Intended Audience :: Developers
Classifier: Operating System :: OS Independent
Classifier: Programming Language :: Python
Classifier: Programming Language :: Python :: 3
Classifier: Programming Language :: Python :: 3.3
Classifier: Programming Language :: Python :: 3.4
Classifier: Programming Language :: Python :: 3.5
Requires-Dist: clint
Requires-Dist: gensim
Requires-Dist: joblib
Requires-Dist: msgpack-rpc-python (==0.4)
Requires-Dist: numpy
Requires-Dist: pymystem3
Requires-Dist: requests
